stdoutools/__init__.py
stdoutools-0.1.0.dist-info/licenses/LICENSE.txt
stdoutools-0.1.0.dist-info/METADATA
stdoutools-0.1.0.dist-info/WHEEL
stdoutools-0.1.0.dist-info/top_level.txt
stdoutools-0.1.0.dist-info/RECORD
