Metadata-Version: 2.4
Name: stdoutools
Version: 0.1.0
Summary: Tools for the python system output, or stdout.
Home-page: https://github.com/Junowu-125/stdoutools
Author: Juno Wu
Author-email: Juno <junowu125@gmail.com>
License: MIT
Requires-Python: >=3.13
License-File: LICENSE.txt
Dynamic: license-file
